LICENSE
MANIFEST.in
README.rst
setup.cfg
setup.py
src/testing/__init__.py
src/testing/cassandra3.py
src/testing.cassandra3.egg-info/PKG-INFO
src/testing.cassandra3.egg-info/SOURCES.txt
src/testing.cassandra3.egg-info/dependency_links.txt
src/testing.cassandra3.egg-info/namespace_packages.txt
src/testing.cassandra3.egg-info/requires.txt
src/testing.cassandra3.egg-info/top_level.txt