Metadata-Version: 1.1
Name: testing.cassandra3
Version: 1.3.0
Summary: automatically setups a cassandra instance in a temporary directory, and destroys it after testing
Home-page: https://github.com/criteo-forks/testing.cassandra
Author: Corentin Chary
Author-email: corentin.chary@gmail.com
License: Apache License 2.0
Platform: UNKNOWN
Classifier: Development Status :: 4 - Beta
Classifier: Intended Audience :: Developers
Classifier: License :: OSI Approved :: Apache Software License
Classifier: Programming Language :: Python
Classifier: Programming Language :: Python :: 2.7
Classifier: Programming Language :: Python :: 3
Classifier: Programming Language :: Python :: 3.5
Classifier: Programming Language :: Python :: 3.6
Classifier: Topic :: Database
Classifier: Topic :: Software Development
Classifier: Topic :: Software Development :: Testing
